{
  "id": "complaint",
  "name": "Complaint form",
  "category": "Complaint",
  "language": "hi-IN",
  "fields": [
    {"name": "Name", "type": "text", "required": true, "hint": "Full name"},
    {"name": "Phone", "type": "phone", "required": true, "hint": "10-digit mobile number"},
    {"name": "Address", "type": "text", "required": true, "hint": "Full address with flat/area"},
    {"name": "Complaint", "type": "textarea", "required": true, "hint": "Describe the problem"},
    {"name": "Priority", "type": "text", "required": false, "hint": "High / Medium / Low"}
  ]
}

